LICENSE
README.md
setup.py
courseSelector/__init__.py
courseSelector/functions.py
courseSelector/globalVariable.py
courseSelector/login.py
courseSelector/main.py
courseSelector/myHttp.py
courseSelector.egg-info/PKG-INFO
courseSelector.egg-info/SOURCES.txt
courseSelector.egg-info/dependency_links.txt
courseSelector.egg-info/requires.txt
courseSelector.egg-info/top_level.txt