Metadata-Version: 2.1
Name: courseSelector
Version: 1.1.2
Summary: An automatic course selection program for SJTU-JI
Home-page: https://github.com/jtc1246/courseSelector
Author: Tiancheng Jiao
Author-email: jtc1246@outlook.com
License: GPL-2.0 License
Platform: all
Requires-Python: >=3
License-File: LICENSE
